fungen/__init__.py
fungen/gene.py
fungen/genome.py
fungen/skeleton.py
fungen/util.py
fungen-0.0.6.dist-info/AUTHORS.rst
fungen-0.0.6.dist-info/LICENSE.txt
fungen-0.0.6.dist-info/METADATA
fungen-0.0.6.dist-info/WHEEL
fungen-0.0.6.dist-info/entry_points.txt
fungen-0.0.6.dist-info/top_level.txt
fungen-0.0.6.dist-info/RECORD
