Metadata-Version: 2.1
Name: fungen
Version: 0.0.6
Summary: FUNctional GENomics
Home-page: https://gitee.com/zhouyulab/fungen/
Author: Yu Zhou
Author-email: yu.zhou@whu.edu.cn
License: mit
Project-URL: Documentation, https://gitee.com/zhouyulab/fungen/
Platform: any
Classifier: Development Status :: 4 - Beta
Classifier: Programming Language :: Python
Provides-Extra: testing
Requires-Dist: pytest ; extra == 'testing'
Requires-Dist: pytest-cov ; extra == 'testing'
